carbon_framework/__init__.py
carbon_framework/version.py
carbon_framework-0.1.2.dist-info/METADATA
carbon_framework-0.1.2.dist-info/WHEEL
carbon_framework-0.1.2.dist-info/RECORD
