Metadata-Version: 2.1
Name: carbon-framework
Version: 0.1.2
Summary: Yet another python framework
Author: Mahdi Zareie
Requires-Python: >=3.12,<4.0
Classifier: Programming Language :: Python :: 3
Classifier: Programming Language :: Python :: 3.12
Classifier: Programming Language :: Python :: 3.13
